letov/__init__.py
letov/cli.py
letov/encoder.py
letov/formatter.py
letov/output/__init__.py
letov/output/fluent.py
letov/output/stdout.py
letov-2.1.3.dist-info/entry_points.txt
letov-2.1.3.dist-info/WHEEL
letov-2.1.3.dist-info/METADATA
letov-2.1.3.dist-info/RECORD
